{
  "dataset": "gen_100",
  "best_value": 0.7598238482384825,
  "best_params": {
    "ae_hidden": 48,
    "cle_hidden1": 192,
    "cle_hidden2": 512,
    "cle_hidden3": 256,
    "ae_dropout": 0.1,
    "epochs": 100,
    "batch_size": 64,
    "lr": 0.00034616703112173554,
    "weight_decay": 0.00028182124367047884,
    "lamda1": 0.8,
    "lamda2": 0.8,
    "optimizer": "sgd",
    "normalize_method": "running_average",
    "score_norm_method": "rank",
    "normalize_loss": false,
    "normalize_scores": true
  },
  "n_trials": 50,
  "study_name": "anomalydae_cle_tuning_gen_100_20251231_155221"
}