{
  "dataset": "reddit",
  "best_value": 0.608297900153055,
  "best_params": {
    "guide_hidden_a": 32,
    "guide_hidden_s": 4,
    "guide_num_layers": 2,
    "guide_dropout": 0.1,
    "guide_alpha": 0.7,
    "cle_hidden1": 384,
    "cle_hidden2": 384,
    "cle_hidden3": 384,
    "epochs": 125,
    "batch_size": 32,
    "lamda1": 0.8,
    "lamda2": 0.5,
    "normalize_method": "z_score",
    "score_norm_method": "rank",
    "normalize_loss": true,
    "normalize_scores": true,
    "use_complex_motif": null
  },
  "n_trials": 100,
  "study_name": "guide_cle_tuning_reddit_20260113_212933"
}